<annotation><folder>Frames</folder><filename>photo286.jpg</filename><path>C:\Users\PC\Politechnika Wroc&#322;awska\In&#380;ynieria system&#243;w\Semestr 5\Przetwarzanie obraz&#243;w i widzenie komputerowe\Laboratorium\koci_projekt\prepared_photos\photo286.jpg</path><source><database>Unknown</database></source><size><width>200</width><height>200</height><depth>3</depth></size><segmented>0</segmented><object><name>awake</name><pose>Unspecified</pose><truncated>0</truncated><difficult>0</difficult><bndbox><xmin>58.520081985828476</xmin><ymin>93.43094825744629</ymin><xmax>158.95351439483406</xmax><ymax>163.09261322021484</ymax></bndbox></object></annotation>